jirafrog/__init__.py
jirafrog/main.py
jirafrog-0.2.2.dist-info/entry_points.txt
jirafrog-0.2.2.dist-info/LICENSE
jirafrog-0.2.2.dist-info/WHEEL
jirafrog-0.2.2.dist-info/METADATA
jirafrog-0.2.2.dist-info/RECORD
